pgmax/__init__.py
pgmax/factor/__init__.py
pgmax/factor/enum.py
pgmax/factor/factor.py
pgmax/factor/logical.py
pgmax/factor/pool.py
pgmax/factor/update_utils.py
pgmax/fgraph/__init__.py
pgmax/fgraph/fgraph.py
pgmax/fgroup/__init__.py
pgmax/fgroup/enum.py
pgmax/fgroup/fgroup.py
pgmax/fgroup/logical.py
pgmax/fgroup/pool.py
pgmax/infer/__init__.py
pgmax/infer/bp.py
pgmax/infer/bp_state.py
pgmax/infer/dual_lp.py
pgmax/infer/energy.py
pgmax/infer/inferer.py
pgmax/utils/__init__.py
pgmax/utils/primal_lp.py
pgmax/vgroup/__init__.py
pgmax/vgroup/varray.py
pgmax/vgroup/vdict.py
pgmax/vgroup/vgroup.py
tests/__init__.py
tests/test_clipping.py
tests/test_energy.py
tests/test_examples.py
tests/test_pgmax.py
pgmax-0.6.1.dist-info/LICENSE
pgmax-0.6.1.dist-info/METADATA
pgmax-0.6.1.dist-info/WHEEL
pgmax-0.6.1.dist-info/top_level.txt
pgmax-0.6.1.dist-info/RECORD
