Metadata-Version: 2.1
Name: pgmax
Version: 0.6.1
Summary: Loopy belief propagation for factor graphs on discrete variables in JAX
Author: DeepMind
Author-email: pgmax-dev@google.com
License: Apache 2.0
License-File: LICENSE
Requires-Dist: jupyter >=1.0.0
Requires-Dist: matplotlib >=3.2.0
Requires-Dist: jax >=0.2.25
Requires-Dist: jaxlib >=0.1.74
Requires-Dist: numba >=0.55.0
Requires-Dist: numpy >=1.21.0
Requires-Dist: scipy >=1.2.3
Requires-Dist: jupytext >=1.11.3
Requires-Dist: tqdm >=4.61.0
Requires-Dist: sphinx >=4.4.0
Requires-Dist: scikit-learn >=1.0.1
Requires-Dist: joblib >=1.1.0
Requires-Dist: pytest >=7.0.1
Requires-Dist: pytest-env >=0.6.2
Requires-Dist: pre-commit >=2.13.0
Requires-Dist: sphinx-rtd-theme >=0.5.2
Requires-Dist: sphinx-book-theme >=0.3.3
Requires-Dist: pytest-cov >=2.12.1
Requires-Dist: tensorflow-datasets >=4.6.0
Requires-Dist: tensorflow >=2.9.1
Requires-Dist: cvxpy >=1.2.0
Requires-Dist: typing-extensions ; python_version >= "3.8"
